


[{"fid":322348,"round":9,"stime":"2011-10-22 19:45","hid":978,"gid":511,"hscore":2,"gscore":2,"hhalfscore":0,"ghalfscore":2,"status":5,"hname":"\u72fc\u961f","hsxname":"\u72fc  \u961f","gname":"\u65af\u65fa\u897f","gsxname":"\u65af\u65fa\u897f","win":1.96,"draw":3.29,"lost":3.79,"handline":"\u534a\u7403","color":"lblue","pan":"\u8f93","hstanding":16,"gstanding":13},{"fid":322340,"round":9,"stime":"2011-10-22 22:00","hid":555,"gid":1284,"hscore":1,"gscore":2,"hhalfscore":1,"ghalfscore":1,"status":5,"hname":"\u963f\u65af\u987f\u7ef4\u62c9","hsxname":"\u7ef4  \u62c9","gname":"\u897f\u5e03\u7f57\u59c6\u7ef4\u5947","gsxname":"\u897f\u5e03\u7f57","win":2.01,"draw":3.24,"lost":3.67,"handline":"\u534a\u7403","color":"lblue","pan":"\u8f93","hstanding":8,"gstanding":12},{"fid":322342,"round":9,"stime":"2011-10-22 22:00","hid":704,"gid":466,"hscore":0,"gscore":2,"hhalfscore":0,"ghalfscore":0,"status":5,"hname":"\u535a\u5c14\u987f","hsxname":"\u535a\u5c14\u987f","gname":"\u6851\u5fb7\u5170","gsxname":"\u6851\u5fb7\u5170","win":2.2,"draw":3.2,"lost":3.22,"handline":"\u5e73\u624b\/\u534a\u7403","color":"lblue","pan":"\u8f93","hstanding":18,"gstanding":17},{"fid":322346,"round":9,"stime":"2011-10-22 22:00","hid":1137,"gid":1258,"hscore":1,"gscore":0,"hhalfscore":0,"ghalfscore":0,"status":5,"hname":"\u7ebd\u5361\u65af\u5c14\u8054","hsxname":"\u7ebd\u5361\u65af","gname":"\u7ef4\u5188\u7ade\u6280","gsxname":"\u7ef4  \u5188","win":1.55,"draw":3.73,"lost":6.12,"handline":"\u4e00\u7403","color":"lgreen","pan":"\u8d70\u76d8","hstanding":4,"gstanding":19},{"fid":322344,"round":9,"stime":"2011-10-23 00:30","hid":1011,"gid":1144,"hscore":1,"gscore":1,"hhalfscore":1,"ghalfscore":0,"status":5,"hname":"\u5229\u7269\u6d66","hsxname":"\u5229\u7269\u6d66","gname":"\u8bfa\u7ef4\u5947","gsxname":"\u8bfa\u7ef4\u5947","win":1.27,"draw":5.09,"lost":10.5,"handline":"\u7403\u534a","color":"lblue","pan":"\u8f93","hstanding":5,"gstanding":9},{"fid":322339,"round":9,"stime":"2011-10-23 20:30","hid":554,"gid":1197,"hscore":3,"gscore":1,"hhalfscore":1,"ghalfscore":1,"status":5,"hname":"\u963f\u68ee\u7eb3","hsxname":"\u963f\u68ee\u7eb3","gname":"\u65af\u6258\u514b\u57ce","gsxname":"\u65af\u6258\u514b","win":1.53,"draw":3.77,"lost":6.19,"handline":"\u4e00\u7403","color":"lred","pan":"\u8d62","hstanding":11,"gstanding":7},{"fid":322343,"round":9,"stime":"2011-10-23 20:30","hid":811,"gid":565,"hscore":1,"gscore":3,"hhalfscore":0,"ghalfscore":1,"status":5,"hname":"\u5bcc\u52d2\u59c6","hsxname":"\u5bcc\u52d2\u59c6","gname":"\u57c3\u5f17\u987f","gsxname":"\u57c3\u5f17\u987f","win":2.29,"draw":3.18,"lost":3.07,"handline":"\u5e73\u624b\/\u534a\u7403","color":"lblue","pan":"\u8f93","hstanding":16,"gstanding":17},{"fid":322345,"round":9,"stime":"2011-10-23 20:30","hid":1075,"gid":1072,"hscore":1,"gscore":6,"hhalfscore":0,"ghalfscore":1,"status":5,"hname":"\u66fc\u5f7b\u65af\u7279\u8054","hsxname":"\u66fc  \u8054","gname":"\u66fc\u5f7b\u65af\u7279\u57ce","gsxname":"\u66fc  \u57ce","win":2.06,"draw":3.24,"lost":3.55,"handline":"\u534a\u7403","color":"lblue","pan":"\u8f93","hstanding":2,"gstanding":1},{"fid":322341,"round":9,"stime":"2011-10-23 22:00","hid":723,"gid":1238,"hscore":1,"gscore":2,"hhalfscore":1,"ghalfscore":1,"status":5,"hname":"\u5e03\u83b1\u514b\u672c","hsxname":"\u5e03\u83b1\u514b","gname":"\u6258\u7279\u7eb3\u59c6\u70ed\u523a","gsxname":"\u70ed  \u523a","win":4.04,"draw":3.44,"lost":1.85,"handline":"\u53d7\u534a\u7403","color":"lblue","pan":"\u8f93","hstanding":19,"gstanding":6},{"fid":322347,"round":9,"stime":"2011-10-23 23:00","hid":954,"gid":1173,"hscore":1,"gscore":0,"hhalfscore":1,"ghalfscore":0,"status":5,"hname":"\u5973\u738b\u516c\u56ed\u5de1\u6e38\u8005","hsxname":"\u5de1\u6e38\u8005","gname":"\u5207\u5c14\u897f","gsxname":"\u5207\u5c14\u897f","win":8.82,"draw":4.55,"lost":1.34,"handline":"\u53d7\u7403\u534a","color":"lred","pan":"\u8d62","hstanding":14,"gstanding":3}]