


[{"fid":824967,"round":23,"stime":"2020-02-22 03:30","hid":664,"gid":1922,"hscore":3,"gscore":2,"hhalfscore":1,"ghalfscore":1,"status":5,"hname":"\u62dc\u4ec1\u6155\u5c3c\u9ed1","hsxname":"\u62dc  \u4ec1","gname":"\u5e15\u5fb7\u535a\u6069","gsxname":"\u5e15\u5fb7\u535a","win":1.06,"draw":14.21,"lost":32.71,"handline":"\u4e09\u7403\/\u4e09\u7403\u534a","color":"lblue","pan":"\u8f93","hstanding":1,"gstanding":18},{"fid":824971,"round":23,"stime":"2020-02-22 22:30","hid":1089,"gid":1869,"hscore":1,"gscore":1,"hhalfscore":1,"ghalfscore":0,"status":5,"hname":"\u95e8\u5174\u683c\u62c9\u5fb7\u5df4\u8d6b","hsxname":"\u95e8  \u5174","gname":"\u970d\u82ac\u6d77\u59c6","gsxname":"\u970d\u82ac\u6d77","win":1.6,"draw":4.36,"lost":5.02,"handline":"\u4e00\u7403","color":"lblue","pan":"\u8f93","hstanding":4,"gstanding":8},{"fid":824977,"round":23,"stime":"2020-02-22 22:30","hid":1334,"gid":786,"hscore":0,"gscore":2,"hhalfscore":0,"ghalfscore":0,"status":5,"hname":"\u4e91\u8fbe\u4e0d\u83b1\u6885","hsxname":"\u4e0d\u6765\u6885","gname":"\u591a\u7279\u8499\u5fb7","gsxname":"\u591a  \u7279","win":6.72,"draw":5.24,"lost":1.4,"handline":"\u53d7\u7403\u534a","color":"lblue","pan":"\u8f93","hstanding":17,"gstanding":3},{"fid":824979,"round":23,"stime":"2020-02-22 22:30","hid":659,"gid":932,"hscore":0,"gscore":5,"hhalfscore":0,"ghalfscore":3,"status":5,"hname":"\u67cf\u6797\u8d6b\u5854","hsxname":"\u8d6b  \u5854","gname":"\u79d1\u9686","gsxname":"\u79d1  \u9686","win":2.53,"draw":3.33,"lost":2.79,"handline":"\u5e73\u624b","color":"lblue","pan":"\u8f93","hstanding":13,"gstanding":14},{"fid":824981,"round":23,"stime":"2020-02-22 22:30","hid":804,"gid":781,"hscore":0,"gscore":2,"hhalfscore":0,"ghalfscore":1,"status":5,"hname":"\u5f17\u8d56\u5821","hsxname":"\u5f17\u8d56\u5821","gname":"\u675c\u585e\u5c14\u591a\u592b","gsxname":"\u675c\u585e\u5c14","win":1.89,"draw":3.7,"lost":3.94,"handline":"\u534a\u7403","color":"lblue","pan":"\u8f93","hstanding":7,"gstanding":16},{"fid":824983,"round":23,"stime":"2020-02-23 01:30","hid":478,"gid":970,"hscore":0,"gscore":5,"hhalfscore":0,"ghalfscore":1,"status":5,"hname":"\u6c99\u5c14\u514b04","hsxname":"\u6c99\u5c14\u514b","gname":"\u83b1\u6bd4\u9521\u7ea2\u725b","gsxname":"\u83b1\u6bd4\u9521","win":3.95,"draw":3.9,"lost":1.84,"handline":"\u53d7\u534a\u7403\/\u4e00\u7403","color":"lblue","pan":"\u8f93","hstanding":6,"gstanding":3},{"fid":824969,"round":23,"stime":"2020-02-23 22:30","hid":986,"gid":1923,"hscore":2,"gscore":0,"hhalfscore":1,"ghalfscore":0,"status":5,"hname":"\u52d2\u6c83\u5e93\u68ee","hsxname":"\u52d2  \u6c83","gname":"\u5965\u683c\u65af\u5821","gsxname":"\u5965\u683c\u65af","win":1.5,"draw":4.62,"lost":5.9,"handline":"\u4e00\u7403\/\u7403\u534a","color":"lred","pan":"\u8d62","hstanding":5,"gstanding":11},{"fid":824973,"round":23,"stime":"2020-02-24 01:00","hid":1269,"gid":1088,"hscore":4,"gscore":0,"hhalfscore":2,"ghalfscore":0,"status":5,"hname":"\u6c83\u5c14\u592b\u65af\u5821","hsxname":"\u6c83\u5c14\u592b","gname":"\u7f8e\u56e0\u8328","gsxname":"\u7f8e\u56e0\u8328","win":1.84,"draw":3.76,"lost":4.08,"handline":"\u534a\u7403\/\u4e00\u7403","color":"lred","pan":"\u8d62","hstanding":9,"gstanding":15},{"fid":824975,"round":23,"stime":"2020-02-25 03:30","hid":791,"gid":660,"hscore":1,"gscore":2,"hhalfscore":0,"ghalfscore":0,"status":5,"hname":"\u6cd5\u5170\u514b\u798f","hsxname":"\u6cd5\u5170\u514b","gname":"\u67cf\u6797\u8054\u5408","gsxname":"\u67cf\u6797\u8054","win":1.82,"draw":3.72,"lost":4.23,"handline":"\u534a\u7403","color":"lblue","pan":"\u8f93","hstanding":10,"gstanding":12}]