


[{"fid":1041398,"round":22,"stime":"2023-02-04 23:59","hid":647,"gid":1233,"hscore":2,"gscore":1,"hhalfscore":1,"ghalfscore":1,"status":5,"hname":"\u5df4\u9ece\u5723\u65e5\u5c14\u66fc","hsxname":"\u65e5\u5c14\u66fc","gname":"\u56fe\u5362\u5179","gsxname":"\u56fe\u5362\u5179","win":1.37,"draw":5.34,"lost":7.46,"handline":"\u7403\u534a","color":"lblue","pan":"\u8f93","hstanding":1,"gstanding":12},{"fid":1041401,"round":22,"stime":"2023-02-05 02:00","hid":1225,"gid":997,"hscore":1,"gscore":3,"hhalfscore":0,"ghalfscore":1,"status":5,"hname":"\u7279\u9c81\u74e6","hsxname":"\u7279\u9c81\u74e6","gname":"\u91cc\u6602","gsxname":"\u91cc  \u6602","win":5.11,"draw":4.18,"lost":1.62,"handline":"\u53d7\u534a\u7403\/\u4e00\u7403","color":"lblue","pan":"\u8f93","hstanding":16,"gstanding":10},{"fid":1041399,"round":22,"stime":"2023-02-05 04:00","hid":990,"gid":998,"hscore":1,"gscore":3,"hhalfscore":1,"ghalfscore":0,"status":5,"hname":"\u96f7\u6069","hsxname":"\u96f7  \u6069","gname":"\u91cc\u5c14","gsxname":"\u91cc  \u5c14","win":2.37,"draw":3.28,"lost":3.07,"handline":"\u5e73\u624b\/\u534a\u7403","color":"lblue","pan":"\u8f93","hstanding":5,"gstanding":6},{"fid":1041395,"round":22,"stime":"2023-02-05 20:00","hid":944,"gid":1105,"hscore":0,"gscore":2,"hhalfscore":0,"ghalfscore":2,"status":5,"hname":"\u514b\u83b1\u8499","hsxname":"\u514b\u83b1\u8499","gname":"\u6469\u7eb3\u54e5","gsxname":"\u6469\u7eb3\u54e5","win":4.31,"draw":3.68,"lost":1.82,"handline":"\u53d7\u534a\u7403","color":"lblue","pan":"\u8f93","hstanding":10,"gstanding":4},{"fid":1041392,"round":22,"stime":"2023-02-05 22:00","hid":560,"gid":1129,"hscore":0,"gscore":2,"hhalfscore":0,"ghalfscore":0,"status":5,"hname":"\u963f\u96c5\u514b\u8096","hsxname":"\u963f\u96c5\u514b","gname":"\u5357\u7279","gsxname":"\u5357  \u7279","win":2.7,"draw":2.93,"lost":2.92,"handline":"\u5e73\u624b","color":"lblue","pan":"\u8f93","hstanding":17,"gstanding":13},{"fid":1041393,"round":22,"stime":"2023-02-05 22:00","hid":1146,"gid":975,"hscore":0,"gscore":0,"hhalfscore":0,"ghalfscore":0,"status":5,"hname":"\u6b27\u585e\u5c14","hsxname":"\u6b27\u585e\u5c14","gname":"\u5170\u65af","gsxname":"\u5170  \u65af","win":3.83,"draw":3.51,"lost":1.97,"handline":"\u53d7\u534a\u7403","color":"lred","pan":"\u8d62","hstanding":19,"gstanding":11},{"fid":1041396,"round":22,"stime":"2023-02-05 22:00","hid":980,"gid":597,"hscore":0,"gscore":0,"hhalfscore":0,"ghalfscore":0,"status":5,"hname":"\u6d1b\u91cc\u6602","hsxname":"\u6d1b\u91cc\u6602","gname":"\u6602\u70ed","gsxname":"\u6602  \u70ed","win":1.99,"draw":3.44,"lost":3.84,"handline":"\u534a\u7403","color":"lblue","pan":"\u8f93","hstanding":7,"gstanding":20},{"fid":1041400,"round":22,"stime":"2023-02-05 22:00","hid":1194,"gid":1090,"hscore":2,"gscore":0,"hhalfscore":2,"ghalfscore":0,"status":5,"hname":"\u65af\u7279\u62c9\u65af\u5821","hsxname":"\u65af\u7279\u5821","gname":"\u8499\u5f7c\u5229\u57c3","gsxname":"\u8499\u5f7c\u5229","win":2.12,"draw":3.27,"lost":3.64,"handline":"\u534a\u7403","color":"lred","pan":"\u8d62","hstanding":18,"gstanding":14},{"fid":1041394,"round":22,"stime":"2023-02-06 00:05","hid":1593,"gid":979,"hscore":1,"gscore":1,"hhalfscore":0,"ghalfscore":0,"status":5,"hname":"\u5e03\u96f7\u65af\u7279","hsxname":"\u5e03\u96f7\u65af","gname":"\u6717\u65af","gsxname":"\u6717  \u65af","win":4.54,"draw":3.65,"lost":1.79,"handline":"\u53d7\u534a\u7403","color":"lred","pan":"\u8d62","hstanding":15,"gstanding":3},{"fid":1041397,"round":22,"stime":"2023-02-06 03:45","hid":1064,"gid":1134,"hscore":1,"gscore":3,"hhalfscore":0,"ghalfscore":2,"status":5,"hname":"\u9a6c\u8d5b","hsxname":"\u9a6c  \u8d5b","gname":"\u5c3c\u65af","gsxname":"\u5c3c  \u65af","win":1.67,"draw":3.82,"lost":5.27,"handline":"\u534a\u7403\/\u4e00\u7403","color":"lblue","pan":"\u8f93","hstanding":2,"gstanding":9}]