


[{"fid":435178,"round":9,"stime":"2014-10-04 02:50","hid":975,"gid":693,"hscore":1,"gscore":0,"hhalfscore":1,"ghalfscore":0,"status":5,"hname":"\u5170\u65af","hsxname":"\u5170  \u65af","gname":"\u6ce2\u5c14\u591a","gsxname":"\u6ce2\u5c14\u591a","win":3.52,"draw":3.2,"lost":2.1,"handline":"\u53d7\u534a\u7403","color":"lred","pan":"\u8d62","hstanding":19,"gstanding":2},{"fid":435177,"round":9,"stime":"2014-10-04 23:00","hid":908,"gid":1064,"hscore":1,"gscore":2,"hhalfscore":0,"ghalfscore":0,"status":5,"hname":"\u5361\u6602","hsxname":"\u5361  \u6602","gname":"\u9a6c\u8d5b","gsxname":"\u9a6c  \u8d5b","win":3.58,"draw":3.25,"lost":2.06,"handline":"\u53d7\u5e73\u624b\/\u534a\u7403","color":"lblue","pan":"\u8f93","hstanding":14,"gstanding":1},{"fid":435172,"round":9,"stime":"2014-10-05 02:00","hid":6281,"gid":1084,"hscore":3,"gscore":0,"hhalfscore":0,"ghalfscore":0,"status":5,"hname":"\u4f0a\u7ef4\u6069","hsxname":"\u4f0a\u7ef4\u6069","gname":"\u6885\u65af","gsxname":"\u6885  \u65af","win":2.32,"draw":3.09,"lost":3.14,"handline":"\u5e73\u624b\/\u534a\u7403","color":"lred","pan":"\u8d62","hstanding":19,"gstanding":5},{"fid":435175,"round":9,"stime":"2014-10-05 02:00","hid":1134,"gid":1090,"hscore":1,"gscore":1,"hhalfscore":0,"ghalfscore":0,"status":5,"hname":"\u5c3c\u65af","hsxname":"\u5c3c  \u65af","gname":"\u8499\u5f7c\u5229\u57c3","gsxname":"\u8499\u5f7c\u5229","win":2.41,"draw":3.07,"lost":3.01,"handline":"\u5e73\u624b\/\u534a\u7403","color":"lblue","pan":"\u8f93\u534a","hstanding":8,"gstanding":7},{"fid":435176,"round":9,"stime":"2014-10-05 02:00","hid":655,"gid":980,"hscore":0,"gscore":2,"hhalfscore":0,"ghalfscore":0,"status":5,"hname":"\u5df4\u65af\u8482\u4e9a","hsxname":"\u5df4\u65af\u8482","gname":"\u6d1b\u91cc\u6602","gsxname":"\u6d1b\u91cc\u6602","win":2.19,"draw":3.16,"lost":3.33,"handline":"\u5e73\u624b\/\u534a\u7403","color":"lblue","pan":"\u8f93","hstanding":17,"gstanding":18},{"fid":435179,"round":9,"stime":"2014-10-05 02:00","hid":990,"gid":979,"hscore":2,"gscore":0,"hhalfscore":0,"ghalfscore":0,"status":5,"hname":"\u96f7\u6069","hsxname":"\u96f7  \u6069","gname":"\u6717\u65af","gsxname":"\u6717  \u65af","win":1.81,"draw":3.37,"lost":4.45,"handline":"\u534a\u7403","color":"lred","pan":"\u8d62","hstanding":16,"gstanding":15},{"fid":435171,"round":9,"stime":"2014-10-05 20:00","hid":494,"gid":1233,"hscore":0,"gscore":1,"hhalfscore":0,"ghalfscore":1,"status":5,"hname":"\u5723\u57c3\u8482\u5b89","hsxname":"\u57c3\u8482\u5b89","gname":"\u56fe\u5362\u5179","gsxname":"\u56fe\u5362\u5179","win":1.91,"draw":3.29,"lost":4.11,"handline":"\u5e73\u624b\/\u534a\u7403","color":"lblue","pan":"\u8f93","hstanding":7,"gstanding":11},{"fid":435173,"round":9,"stime":"2014-10-05 23:00","hid":813,"gid":1129,"hscore":0,"gscore":1,"hhalfscore":0,"ghalfscore":1,"status":5,"hname":"\u7518\u5188","hsxname":"\u7518  \u5188","gname":"\u5357\u7279","gsxname":"\u5357  \u7279","win":2.58,"draw":2.95,"lost":2.89,"handline":"\u5e73\u624b","color":"lblue","pan":"\u8f93","hstanding":20,"gstanding":9},{"fid":435174,"round":9,"stime":"2014-10-05 23:00","hid":997,"gid":998,"hscore":3,"gscore":0,"hhalfscore":2,"ghalfscore":0,"status":5,"hname":"\u91cc\u6602","hsxname":"\u91cc  \u6602","gname":"\u91cc\u5c14","gsxname":"\u91cc  \u5c14","win":2.08,"draw":3.14,"lost":3.64,"handline":"\u5e73\u624b\/\u534a\u7403","color":"lred","pan":"\u8d62","hstanding":10,"gstanding":3},{"fid":435180,"round":9,"stime":"2014-10-06 03:00","hid":647,"gid":1105,"hscore":1,"gscore":1,"hhalfscore":0,"ghalfscore":0,"status":5,"hname":"\u5df4\u9ece\u5723\u65e5\u5c14\u66fc","hsxname":"\u65e5\u5c14\u66fc","gname":"\u6469\u7eb3\u54e5","gsxname":"\u6469\u7eb3\u54e5","win":1.48,"draw":4.05,"lost":6.82,"handline":"\u4e00\u7403","color":"lblue","pan":"\u8f93","hstanding":5,"gstanding":14}]