


[{"fid":985796,"round":18,"stime":"2022-01-08 03:30","hid":664,"gid":1089,"hscore":1,"gscore":2,"hhalfscore":1,"ghalfscore":2,"status":5,"hname":"\u62dc\u4ec1\u6155\u5c3c\u9ed1","hsxname":"\u62dc  \u4ec1","gname":"\u95e8\u5174\u683c\u62c9\u5fb7\u5df4\u8d6b","gsxname":"\u95e8  \u5174","win":1.3,"draw":6.27,"lost":8.76,"handline":"\u7403\u534a\/\u4e24\u7403","color":"lblue","pan":"\u8f93","hstanding":1,"gstanding":14},{"fid":985795,"round":18,"stime":"2022-01-08 22:30","hid":986,"gid":660,"hscore":2,"gscore":2,"hhalfscore":1,"ghalfscore":1,"status":5,"hname":"\u52d2\u6c83\u5e93\u68ee","hsxname":"\u52d2  \u6c83","gname":"\u67cf\u6797\u8054\u5408","gsxname":"\u67cf\u6797\u8054","win":1.8,"draw":3.82,"lost":4.3,"handline":"\u534a\u7403","color":"lblue","pan":"\u8f93","hstanding":4,"gstanding":7},{"fid":985799,"round":18,"stime":"2022-01-08 22:30","hid":804,"gid":682,"hscore":2,"gscore":2,"hhalfscore":1,"ghalfscore":0,"status":5,"hname":"\u5f17\u8d56\u5821","hsxname":"\u5f17\u8d56\u5821","gname":"\u6bd4\u52d2\u8d39\u5c14\u5fb7","gsxname":"\u6bd4\u52d2\u8d39","win":1.75,"draw":3.68,"lost":4.83,"handline":"\u534a\u7403","color":"lblue","pan":"\u8f93","hstanding":3,"gstanding":17},{"fid":985800,"round":18,"stime":"2022-01-08 22:30","hid":794,"gid":1195,"hscore":0,"gscore":0,"hhalfscore":0,"ghalfscore":0,"status":5,"hname":"\u83f2\u5c14\u7279","hsxname":"\u83f2\u5c14\u7279","gname":"\u65af\u56fe\u52a0\u7279","gsxname":"\u65af\u56fe\u52a0","win":3.44,"draw":3.43,"lost":2.14,"handline":"\u53d7\u5e73\u624b\/\u534a\u7403","color":"lred","pan":"\u8d62\u534a","hstanding":18,"gstanding":16},{"fid":985802,"round":18,"stime":"2022-01-08 22:30","hid":1869,"gid":1923,"hscore":3,"gscore":1,"hhalfscore":2,"ghalfscore":1,"status":5,"hname":"\u970d\u82ac\u6d77\u59c6","hsxname":"\u970d\u82ac\u6d77","gname":"\u5965\u683c\u65af\u5821","gsxname":"\u5965\u683c\u65af","win":1.53,"draw":4.41,"lost":5.89,"handline":"\u4e00\u7403","color":"lred","pan":"\u8d62","hstanding":5,"gstanding":15},{"fid":985803,"round":18,"stime":"2022-01-08 22:30","hid":970,"gid":1088,"hscore":4,"gscore":1,"hhalfscore":1,"ghalfscore":0,"status":5,"hname":"\u83b1\u6bd4\u9521\u7ea2\u725b","hsxname":"\u83b1\u6bd4\u9521","gname":"\u7f8e\u56e0\u8328","gsxname":"\u7f8e\u56e0\u8328","win":1.72,"draw":3.93,"lost":4.69,"handline":"\u534a\u7403\/\u4e00\u7403","color":"lred","pan":"\u8d62","hstanding":10,"gstanding":9},{"fid":985798,"round":18,"stime":"2022-01-09 01:30","hid":791,"gid":786,"hscore":2,"gscore":3,"hhalfscore":2,"ghalfscore":0,"status":5,"hname":"\u6cd5\u5170\u514b\u798f","hsxname":"\u6cd5\u5170\u514b","gname":"\u591a\u7279\u8499\u5fb7","gsxname":"\u591a  \u7279","win":3.75,"draw":3.93,"lost":1.89,"handline":"\u53d7\u534a\u7403\/\u4e00\u7403","color":"lblue","pan":"\u8f93\u534a","hstanding":7,"gstanding":2},{"fid":985801,"round":18,"stime":"2022-01-09 22:30","hid":659,"gid":932,"hscore":1,"gscore":3,"hhalfscore":0,"ghalfscore":2,"status":5,"hname":"\u67cf\u6797\u8d6b\u5854","hsxname":"\u8d6b  \u5854","gname":"\u79d1\u9686","gsxname":"\u79d1  \u9686","win":2.74,"draw":3.44,"lost":2.51,"handline":"\u5e73\u624b","color":"lblue","pan":"\u8f93","hstanding":12,"gstanding":9},{"fid":985797,"round":18,"stime":"2022-01-10 00:30","hid":695,"gid":1269,"hscore":1,"gscore":0,"hhalfscore":0,"ghalfscore":0,"status":5,"hname":"\u6ce2\u9e3f","hsxname":"\u6ce2  \u9e3f","gname":"\u6c83\u5c14\u592b\u65af\u5821","gsxname":"\u6c83\u5c14\u592b","win":3.31,"draw":3.38,"lost":2.21,"handline":"\u53d7\u5e73\u624b\/\u534a\u7403","color":"lred","pan":"\u8d62","hstanding":13,"gstanding":14}]