


[{"fid":831275,"round":24,"stime":"2020-02-15 04:00","hid":1243,"gid":1046,"hscore":2,"gscore":2,"hhalfscore":1,"ghalfscore":2,"status":5,"hname":"\u5df4\u4f26\u897f\u4e9a","hsxname":"\u5df4\u4f26\u897f","gname":"\u9a6c\u5fb7\u91cc\u7ade\u6280","gsxname":"\u9a6c\u7ade\u6280","win":3.34,"draw":3,"lost":2.38,"handline":"","color":"lgreen","pan":"","hstanding":7,"gstanding":4},{"fid":831269,"round":24,"stime":"2020-02-15 20:00","hid":1062,"gid":542,"hscore":1,"gscore":0,"hhalfscore":0,"ghalfscore":0,"status":5,"hname":"\u9a6c\u6d1b\u5361","hsxname":"\u9a6c\u6d1b\u5361","gname":"\u963f\u62c9\u7ef4\u65af","gsxname":"\u963f\u62c9\u7ef4","win":2.58,"draw":3.06,"lost":2.94,"handline":"","color":"lgreen","pan":"","hstanding":18,"gstanding":14},{"fid":831261,"round":24,"stime":"2020-02-15 23:00","hid":653,"gid":838,"hscore":2,"gscore":1,"hhalfscore":2,"ghalfscore":0,"status":5,"hname":"\u5df4\u585e\u7f57\u90a3","hsxname":"\u5df4  \u8428","gname":"\u8d6b\u5854\u8d39","gsxname":"\u8d6b\u5854\u8d39","win":1.39,"draw":4.65,"lost":8.43,"handline":"","color":"lgreen","pan":"","hstanding":2,"gstanding":3},{"fid":831277,"round":24,"stime":"2020-02-16 01:30","hid":683,"gid":985,"hscore":2,"gscore":1,"hhalfscore":1,"ghalfscore":0,"status":5,"hname":"\u6bd4\u5229\u4e9a\u96f7\u4e9a\u5c14","hsxname":"\u6bd4\u5229\u4e9a","gname":"\u83b1\u4e07\u7279","gsxname":"\u83b1\u4e07\u7279","win":1.54,"draw":4.56,"lost":5.45,"handline":"","color":"lgreen","pan":"","hstanding":8,"gstanding":11},{"fid":831265,"round":24,"stime":"2020-02-16 04:00","hid":4607,"gid":1241,"hscore":2,"gscore":1,"hhalfscore":0,"ghalfscore":0,"status":5,"hname":"\u683c\u62c9\u7eb3\u8fbeCF","hsxname":"\u683c\u62c9\u7eb3","gname":"\u5df4\u5229\u4e9a\u591a\u5229\u5fb7","gsxname":"\u5df4\u5229\u4e9a","win":2.41,"draw":2.87,"lost":3.45,"handline":"","color":"lgreen","pan":"","hstanding":10,"gstanding":15},{"fid":831273,"round":24,"stime":"2020-02-16 19:00","hid":464,"gid":1283,"hscore":2,"gscore":2,"hhalfscore":1,"ghalfscore":1,"status":5,"hname":"\u585e\u7ef4\u5229\u4e9a","hsxname":"\u585e\u7ef4\u5229","gname":"\u897f\u73ed\u7259\u4eba","gsxname":"\u897f\u7259\u4eba","win":1.53,"draw":3.99,"lost":6.71,"handline":"","color":"lgreen","pan":"","hstanding":5,"gstanding":20},{"fid":831267,"round":24,"stime":"2020-02-16 21:00","hid":971,"gid":673,"hscore":0,"gscore":0,"hhalfscore":0,"ghalfscore":0,"status":5,"hname":"\u83b1\u52a0\u5185\u65af","hsxname":"\u83b1\u52a0\u5185","gname":"\u7687\u5bb6\u8d1d\u8482\u65af","gsxname":"\u8d1d\u8482\u65af","win":2.46,"draw":3.11,"lost":3.06,"handline":"","color":"lgreen","pan":"","hstanding":19,"gstanding":13},{"fid":831259,"round":24,"stime":"2020-02-17 01:30","hid":690,"gid":622,"hscore":0,"gscore":1,"hhalfscore":0,"ghalfscore":1,"status":5,"hname":"\u6bd5\u5c14\u5df4\u9102\u7ade\u6280","hsxname":"\u6bd5\u5c14\u5df4","gname":"\u5965\u8428\u82cf\u7eb3","gsxname":"\u5965\u8428\u82cf","win":1.88,"draw":3.28,"lost":4.67,"handline":"","color":"lgreen","pan":"","hstanding":10,"gstanding":13},{"fid":831271,"round":24,"stime":"2020-02-17 04:00","hid":883,"gid":457,"hscore":2,"gscore":2,"hhalfscore":0,"ghalfscore":1,"status":5,"hname":"\u7687\u5bb6\u9a6c\u5fb7\u91cc","hsxname":"\u7687  \u9a6c","gname":"\u7ef4\u6208\u585e\u5c14\u5854","gsxname":"\u585e\u5c14\u5854","win":1.23,"draw":6.33,"lost":12.27,"handline":"","color":"lgreen","pan":"","hstanding":1,"gstanding":18},{"fid":831263,"round":24,"stime":"2020-03-11 03:00","hid":562,"gid":885,"hscore":1,"gscore":2,"hhalfscore":0,"ghalfscore":1,"status":5,"hname":"\u57c3\u74e6\u5c14","hsxname":"\u57c3\u74e6\u5c14","gname":"\u7687\u5bb6\u793e\u4f1a","gsxname":"\u793e  \u4f1a","win":3.35,"draw":3.34,"lost":2.22,"handline":"\u53d7\u534a\u7403","color":"lblue","pan":"\u8f93","hstanding":16,"gstanding":6}]