


[{"fid":606890,"round":6,"stime":"2016-09-24 02:45","hid":673,"gid":1056,"hscore":1,"gscore":0,"hhalfscore":1,"ghalfscore":0,"status":5,"hname":"\u7687\u5bb6\u8d1d\u8482\u65af","hsxname":"\u8d1d\u8482\u65af","gname":"\u9a6c\u62c9\u52a0","gsxname":"\u9a6c\u62c9\u52a0","win":2.51,"draw":3.16,"lost":2.95,"handline":"\u5e73\u624b","color":"lred","pan":"\u8d62","hstanding":16,"gstanding":14},{"fid":606891,"round":6,"stime":"2016-09-24 19:00","hid":562,"gid":885,"hscore":2,"gscore":0,"hhalfscore":0,"ghalfscore":0,"status":5,"hname":"\u57c3\u74e6\u5c14","hsxname":"\u57c3\u74e6\u5c14","gname":"\u7687\u5bb6\u793e\u4f1a","gsxname":"\u793e  \u4f1a","win":2.59,"draw":3.15,"lost":2.85,"handline":"\u5e73\u624b","color":"lred","pan":"\u8d62","hstanding":10,"gstanding":9},{"fid":606893,"round":6,"stime":"2016-09-24 22:15","hid":1290,"gid":653,"hscore":0,"gscore":5,"hhalfscore":0,"ghalfscore":2,"status":5,"hname":"\u5e0c\u6d2a\u7ade\u6280","hsxname":"\u5e0c  \u6d2a","gname":"\u5df4\u585e\u7f57\u90a3","gsxname":"\u5df4  \u8428","win":12.25,"draw":6.15,"lost":1.24,"handline":"\u53d7\u7403\u534a\/\u4e24\u7403","color":"lblue","pan":"\u8f93","hstanding":12,"gstanding":3},{"fid":606888,"round":6,"stime":"2016-09-25 00:30","hid":690,"gid":464,"hscore":3,"gscore":1,"hhalfscore":1,"ghalfscore":0,"status":5,"hname":"\u6bd5\u5c14\u5df4\u9102\u7ade\u6280","hsxname":"\u6bd5\u5c14\u5df4","gname":"\u585e\u7ef4\u5229\u4e9a","gsxname":"\u585e\u7ef4\u5229","win":2.03,"draw":3.39,"lost":3.8,"handline":"\u534a\u7403","color":"lred","pan":"\u8d62","hstanding":8,"gstanding":3},{"fid":606894,"round":6,"stime":"2016-09-25 02:45","hid":965,"gid":883,"hscore":2,"gscore":2,"hhalfscore":1,"ghalfscore":1,"status":5,"hname":"\u62c9\u65af\u5e15\u5c14\u9a6c\u65af","hsxname":"\u62c9\u65af\u5e15","gname":"\u7687\u5bb6\u9a6c\u5fb7\u91cc","gsxname":"\u7687  \u9a6c","win":8.39,"draw":5.49,"lost":1.33,"handline":"\u53d7\u7403\u534a","color":"lred","pan":"\u8d62","hstanding":7,"gstanding":2},{"fid":606895,"round":6,"stime":"2016-09-25 18:00","hid":971,"gid":1243,"hscore":1,"gscore":2,"hhalfscore":1,"ghalfscore":1,"status":5,"hname":"\u83b1\u52a0\u5185\u65af","hsxname":"\u83b1\u52a0\u5185","gname":"\u5df4\u4f26\u897f\u4e9a","gsxname":"\u5df4\u4f26\u897f","win":2.94,"draw":3.25,"lost":2.46,"handline":"\u53d7\u5e73\u624b\/\u534a\u7403","color":"lblue","pan":"\u8f93","hstanding":11,"gstanding":18},{"fid":606889,"round":6,"stime":"2016-09-25 22:15","hid":1046,"gid":959,"hscore":1,"gscore":0,"hhalfscore":0,"ghalfscore":0,"status":5,"hname":"\u9a6c\u5fb7\u91cc\u7ade\u6280","hsxname":"\u9a6c\u7ade\u6280","gname":"\u62c9\u79d1\u9c81\u5c3c\u4e9a","gsxname":"\u62c9\u79d1\u9c81","win":1.2,"draw":6.26,"lost":17.35,"handline":"\u7403\u534a\/\u4e24\u7403","color":"lblue","pan":"\u8f93","hstanding":7,"gstanding":15},{"fid":606896,"round":6,"stime":"2016-09-26 00:30","hid":683,"gid":622,"hscore":3,"gscore":1,"hhalfscore":3,"ghalfscore":1,"status":5,"hname":"\u6bd4\u5229\u4e9a\u96f7\u4e9a\u5c14","hsxname":"\u6bd4\u5229\u4e9a","gname":"\u5965\u8428\u82cf\u7eb3","gsxname":"\u5965\u8428\u82cf","win":1.38,"draw":4.6,"lost":9.26,"handline":"\u4e00\u7403\/\u7403\u534a","color":"lred","pan":"\u8d62","hstanding":8,"gstanding":20},{"fid":606892,"round":6,"stime":"2016-09-26 02:45","hid":1283,"gid":457,"hscore":0,"gscore":2,"hhalfscore":0,"ghalfscore":0,"status":5,"hname":"\u897f\u73ed\u7259\u4eba","hsxname":"\u897f\u7259\u4eba","gname":"\u7ef4\u6208\u585e\u5c14\u5854","gsxname":"\u585e\u5c14\u5854","win":2.28,"draw":3.27,"lost":3.22,"handline":"\u5e73\u624b\/\u534a\u7403","color":"lblue","pan":"\u8f93","hstanding":16,"gstanding":18},{"fid":606887,"round":6,"stime":"2016-09-27 02:45","hid":542,"gid":4607,"hscore":3,"gscore":1,"hhalfscore":0,"ghalfscore":0,"status":5,"hname":"\u963f\u62c9\u7ef4\u65af","hsxname":"\u963f\u62c9\u7ef4","gname":"\u683c\u62c9\u7eb3\u8fbeCF","gsxname":"\u683c\u62c9\u7eb3","win":1.93,"draw":3.39,"lost":4.19,"handline":"\u534a\u7403","color":"lred","pan":"\u8d62","hstanding":14,"gstanding":19}]