


[{"fid":398240,"round":23,"stime":"2014-02-01 03:30","hid":647,"gid":693,"hscore":2,"gscore":0,"hhalfscore":0,"ghalfscore":0,"status":5,"hname":"\u5df4\u9ece\u5723\u65e5\u5c14\u66fc","hsxname":"\u65e5\u5c14\u66fc","gname":"\u6ce2\u5c14\u591a","gsxname":"\u6ce2\u5c14\u591a","win":1.23,"draw":5.72,"lost":11.78,"handline":"\u7403\u534a\/\u4e24\u7403","color":"lred","pan":"\u8d62\u534a","hstanding":1,"gstanding":7},{"fid":398237,"round":23,"stime":"2014-02-01 23:30","hid":980,"gid":1105,"hscore":2,"gscore":2,"hhalfscore":1,"ghalfscore":1,"status":5,"hname":"\u6d1b\u91cc\u6602","hsxname":"\u6d1b\u91cc\u6602","gname":"\u6469\u7eb3\u54e5","gsxname":"\u6469\u7eb3\u54e5","win":3.55,"draw":3.2,"lost":2.08,"handline":"\u53d7\u5e73\u624b\/\u534a\u7403","color":"lred","pan":"\u8d62\u534a","hstanding":9,"gstanding":2},{"fid":398235,"round":23,"stime":"2014-02-02 03:00","hid":655,"gid":813,"hscore":3,"gscore":2,"hhalfscore":0,"ghalfscore":0,"status":5,"hname":"\u5df4\u65af\u8482\u4e9a","hsxname":"\u5df4\u65af\u8482","gname":"\u7518\u5188","gsxname":"\u7518  \u5188","win":2.17,"draw":3.11,"lost":3.41,"handline":"\u5e73\u624b\/\u534a\u7403","color":"lred","pan":"\u8d62","hstanding":10,"gstanding":14},{"fid":398236,"round":23,"stime":"2014-02-02 03:00","hid":6281,"gid":560,"hscore":1,"gscore":1,"hhalfscore":0,"ghalfscore":0,"status":5,"hname":"\u4f0a\u7ef4\u6069","hsxname":"\u4f0a\u7ef4\u6069","gname":"\u963f\u96c5\u514b\u8096","gsxname":"\u963f\u96c5\u514b","win":1.63,"draw":3.62,"lost":5.51,"handline":"\u534a\u7403\/\u4e00\u7403","color":"lblue","pan":"\u8f93","hstanding":17,"gstanding":20},{"fid":398241,"round":23,"stime":"2014-02-02 03:00","hid":975,"gid":1090,"hscore":2,"gscore":4,"hhalfscore":0,"ghalfscore":1,"status":5,"hname":"\u5170\u65af","hsxname":"\u5170  \u65af","gname":"\u8499\u5f7c\u5229\u57c3","gsxname":"\u8499\u5f7c\u5229","win":2.66,"draw":3.04,"lost":2.71,"handline":"\u5e73\u624b","color":"lblue","pan":"\u8f93","hstanding":8,"gstanding":15},{"fid":398243,"round":23,"stime":"2014-02-02 03:00","hid":494,"gid":2331,"hscore":3,"gscore":0,"hhalfscore":1,"ghalfscore":0,"status":5,"hname":"\u5723\u57c3\u8482\u5b89","hsxname":"\u57c3\u8482\u5b89","gname":"\u74e6\u6717\u8c22\u7eb3","gsxname":"\u74e6\u6717\u8c22","win":1.47,"draw":3.94,"lost":7.23,"handline":"\u4e00\u7403\/\u7403\u534a","color":"lred","pan":"\u8d62","hstanding":4,"gstanding":18},{"fid":398244,"round":23,"stime":"2014-02-02 03:00","hid":1210,"gid":1129,"hscore":1,"gscore":0,"hhalfscore":1,"ghalfscore":0,"status":5,"hname":"\u7d22\u8096","hsxname":"\u7d22  \u8096","gname":"\u5357\u7279","gsxname":"\u5357  \u7279","win":2.8,"draw":3.05,"lost":2.56,"handline":"\u53d7\u5e73\u624b\/\u534a\u7403","color":"lred","pan":"\u8d62","hstanding":19,"gstanding":11},{"fid":398239,"round":23,"stime":"2014-02-02 21:00","hid":1134,"gid":998,"hscore":1,"gscore":0,"hhalfscore":1,"ghalfscore":0,"status":5,"hname":"\u5c3c\u65af","hsxname":"\u5c3c  \u65af","gname":"\u91cc\u5c14","gsxname":"\u91cc  \u5c14","win":3.28,"draw":3.2,"lost":2.46,"handline":"\u53d7\u5e73\u624b\/\u534a\u7403","color":"lred","pan":"\u8d62","hstanding":13,"gstanding":3},{"fid":398242,"round":23,"stime":"2014-02-02 23:59","hid":990,"gid":997,"hscore":2,"gscore":0,"hhalfscore":1,"ghalfscore":0,"status":5,"hname":"\u96f7\u6069","hsxname":"\u96f7  \u6069","gname":"\u91cc\u6602","gsxname":"\u91cc  \u6602","win":3.01,"draw":3.22,"lost":2.6,"handline":"\u5e73\u624b","color":"lred","pan":"\u8d62","hstanding":16,"gstanding":6},{"fid":398238,"round":23,"stime":"2014-02-03 04:00","hid":1064,"gid":1233,"hscore":2,"gscore":2,"hhalfscore":2,"ghalfscore":1,"status":5,"hname":"\u9a6c\u8d5b","hsxname":"\u9a6c  \u8d5b","gname":"\u56fe\u5362\u5179","gsxname":"\u56fe\u5362\u5179","win":2.03,"draw":3.51,"lost":4.53,"handline":"\u534a\u7403","color":"lblue","pan":"\u8f93","hstanding":5,"gstanding":13}]