


[{"fid":407550,"round":28,"stime":"2014-03-15 04:00","hid":838,"gid":4607,"hscore":3,"gscore":3,"hhalfscore":2,"ghalfscore":1,"status":5,"hname":"\u8d6b\u5854\u8d39","hsxname":"\u8d6b\u5854\u8d39","gname":"\u683c\u62c9\u7eb3\u8fbeCF","gsxname":"\u683c\u62c9\u7eb3","win":2.13,"draw":3.2,"lost":3.48,"handline":"\u5e73\u624b\/\u534a\u7403","color":"lblue","pan":"\u8f93\u534a","hstanding":16,"gstanding":12},{"fid":407553,"round":28,"stime":"2014-03-15 23:00","hid":985,"gid":457,"hscore":0,"gscore":1,"hhalfscore":0,"ghalfscore":1,"status":5,"hname":"\u83b1\u4e07\u7279","hsxname":"\u83b1\u4e07\u7279","gname":"\u7ef4\u6208\u585e\u5c14\u5854","gsxname":"\u585e\u5c14\u5854","win":2.44,"draw":3.14,"lost":2.91,"handline":"\u5e73\u624b\/\u534a\u7403","color":"lblue","pan":"\u8f93","hstanding":10,"gstanding":11},{"fid":407557,"round":28,"stime":"2014-03-16 01:00","hid":650,"gid":532,"hscore":3,"gscore":1,"hhalfscore":1,"ghalfscore":0,"status":5,"hname":"\u5df4\u5217\u5361\u8bfa","hsxname":"\u5df4\u5217\u5361","gname":"\u963f\u5c14\u6885\u91cc\u4e9a","gsxname":"\u963f\u5c14\u6885","win":1.83,"draw":3.47,"lost":4.22,"handline":"\u534a\u7403","color":"lred","pan":"\u8d62","hstanding":19,"gstanding":18},{"fid":407554,"round":28,"stime":"2014-03-16 03:00","hid":1056,"gid":883,"hscore":0,"gscore":1,"hhalfscore":0,"ghalfscore":1,"status":5,"hname":"\u9a6c\u62c9\u52a0","hsxname":"\u9a6c\u62c9\u52a0","gname":"\u7687\u5bb6\u9a6c\u5fb7\u91cc","gsxname":"\u7687  \u9a6c","win":10.66,"draw":5.85,"lost":1.25,"handline":"\u53d7\u7403\u534a\/\u4e24\u7403","color":"lred","pan":"\u8d62","hstanding":13,"gstanding":1},{"fid":407552,"round":28,"stime":"2014-03-16 05:00","hid":1046,"gid":1283,"hscore":1,"gscore":0,"hhalfscore":0,"ghalfscore":0,"status":5,"hname":"\u9a6c\u5fb7\u91cc\u7ade\u6280","hsxname":"\u9a6c\u7ade\u6280","gname":"\u897f\u73ed\u7259\u4eba","gsxname":"\u897f\u7259\u4eba","win":1.31,"draw":4.93,"lost":9.77,"handline":"\u4e00\u7403\/\u7403\u534a","color":"lblue","pan":"\u8f93\u534a","hstanding":2,"gstanding":9},{"fid":407551,"round":28,"stime":"2014-03-16 19:00","hid":564,"gid":673,"hscore":0,"gscore":0,"hhalfscore":0,"ghalfscore":0,"status":5,"hname":"\u57c3\u5c14\u5207","hsxname":"\u57c3\u5c14\u5207","gname":"\u7687\u5bb6\u8d1d\u8482\u65af","gsxname":"\u8d1d\u8482\u65af","win":2.39,"draw":3.17,"lost":2.96,"handline":"\u5e73\u624b\/\u534a\u7403","color":"lblue","pan":"\u8f93\u534a","hstanding":14,"gstanding":20},{"fid":407555,"round":28,"stime":"2014-03-16 23:59","hid":653,"gid":622,"hscore":7,"gscore":0,"hhalfscore":3,"ghalfscore":0,"status":5,"hname":"\u5df4\u585e\u7f57\u90a3","hsxname":"\u5df4  \u8428","gname":"\u5965\u8428\u82cf\u7eb3","gsxname":"\u5965\u8428\u82cf","win":1.05,"draw":12.6,"lost":30.4,"handline":"\u4e09\u7403","color":"lred","pan":"\u8d62","hstanding":3,"gstanding":15},{"fid":407556,"round":28,"stime":"2014-03-17 02:00","hid":464,"gid":1241,"hscore":4,"gscore":1,"hhalfscore":2,"ghalfscore":0,"status":5,"hname":"\u585e\u7ef4\u5229\u4e9a","hsxname":"\u585e\u7ef4\u5229","gname":"\u5df4\u5229\u4e9a\u591a\u5229\u5fb7","gsxname":"\u5df4\u5229\u4e9a","win":1.39,"draw":4.57,"lost":7.59,"handline":"\u4e00\u7403\/\u7403\u534a","color":"lred","pan":"\u8d62","hstanding":7,"gstanding":18},{"fid":407558,"round":28,"stime":"2014-03-17 04:00","hid":885,"gid":1243,"hscore":1,"gscore":0,"hhalfscore":0,"ghalfscore":0,"status":5,"hname":"\u7687\u5bb6\u793e\u4f1a","hsxname":"\u793e  \u4f1a","gname":"\u5df4\u4f26\u897f\u4e9a","gsxname":"\u5df4\u4f26\u897f","win":2.07,"draw":3.38,"lost":3.42,"handline":"\u534a\u7403","color":"lred","pan":"\u8d62","hstanding":6,"gstanding":8},{"fid":407549,"round":28,"stime":"2014-03-18 05:00","hid":683,"gid":690,"hscore":1,"gscore":1,"hhalfscore":0,"ghalfscore":0,"status":5,"hname":"\u6bd4\u5229\u4e9a\u96f7\u4e9a\u5c14","hsxname":"\u6bd4\u5229\u4e9a","gname":"\u6bd5\u5c14\u5df4\u9102\u7ade\u6280","gsxname":"\u6bd5\u5c14\u5df4","win":2.18,"draw":3.28,"lost":3.27,"handline":"\u534a\u7403","color":"lblue","pan":"\u8f93","hstanding":6,"gstanding":4}]